[{"ID_de_la_Cuenta#0":"593096482231018","Nombre_de_la_Cuenta#1":"Nueva America Virtual","Ad_Network#2":"facebook","Estrategia_de_Oferta_de_la_Campaña#3":"LOWEST_COST_WITHOUT_CAP","Clics":"122","CPC__Costo_por_clic_#4":"154.934426","CPM__Costo_por_mil_impresiones_#5":"4980.764163","CTR__Tasa_de_clics_#6":"3.214756","Presupuesto_Diario_de_la_Campaña#7":"12000","Fecha_de_Inicio_de_los_Datos#8":"2024-01-13","Fecha_de_Fin_de_los_Datos#9":"2024-02-11","ID_de_la_Campaña#10":"120204189119320570","Impresiones":"3795","Nombre_de_la_Campaña#11":"FBIG_Tráfico_BH_Lead_Landing","Objetivo_de_la_Campaña#12":"OUTCOME_LEADS","Gasto":"18902","Inicio_de_la_Campaña#13":"2024-02-09T12:13:40-0500","Estado_de_la_Campaña#14":"ACTIVE","Clics_Unicos#15":"105"},{"ID_de_la_Cuenta#0":"593096482231018","Nombre_de_la_Cuenta#1":"Nueva America Virtual","Ad_Network#2":"facebook","Estrategia_de_Oferta_de_la_Campaña#3":"None","Clics":"94","CPC__Costo_por_clic_#4":"692.053191","CPM__Costo_por_mil_impresiones_#5":"6903.64003","CTR__Tasa_de_clics_#6":"0.997559","Presupuesto_Diario_de_la_Campaña#7":"None","Fecha_de_Inicio_de_los_Datos#8":"2024-01-13","Fecha_de_Fin_de_los_Datos#9":"2024-02-11","ID_de_la_Campaña#10":"120204188237770570","Impresiones":"9423","Nombre_de_la_Campaña#11":"FBIG_Técnico_Mercadeo_Enero_2024_Cali","Objetivo_de_la_Campaña#12":"OUTCOME_LEADS","Gasto":"65053","Inicio_de_la_Campaña#13":"2024-02-09T11:25:31-0500","Estado_de_la_Campaña#14":"ACTIVE","Clics_Unicos#15":"72"},{"ID_de_la_Cuenta#0":"593096482231018","Nombre_de_la_Cuenta#1":"Nueva America Virtual","Ad_Network#2":"facebook","Estrategia_de_Oferta_de_la_Campaña#3":"LOWEST_COST_WITHOUT_CAP","Clics":"78","CPC__Costo_por_clic_#4":"619.615385","CPM__Costo_por_mil_impresiones_#5":"5267.000872","CTR__Tasa_de_clics_#6":"0.850044","Presupuesto_Diario_de_la_Campaña#7":"12000","Fecha_de_Inicio_de_los_Datos#8":"2024-01-13","Fecha_de_Fin_de_los_Datos#9":"2024-02-11","ID_de_la_Campaña#10":"120204158087770570","Impresiones":"9176","Nombre_de_la_Campaña#11":"FBIG_Técnico_Marketing_Enero_2024_Cali","Objetivo_de_la_Campaña#12":"OUTCOME_LEADS","Gasto":"48330","Inicio_de_la_Campaña#13":"2024-02-08T18:13:20-0500","Estado_de_la_Campaña#14":"ACTIVE","Clics_Unicos#15":"64"},{"ID_de_la_Cuenta#0":"593096482231018","Nombre_de_la_Cuenta#1":"Nueva America Virtual","Ad_Network#2":"facebook","Estrategia_de_Oferta_de_la_Campaña#3":"LOWEST_COST_WITHOUT_CAP","Clics":"283","CPC__Costo_por_clic_#4":"231.233216","CPM__Costo_por_mil_impresiones_#5":"3126.56474","CTR__Tasa_de_clics_#6":"1.352126","Presupuesto_Diario_de_la_Campaña#7":"20000","Fecha_de_Inicio_de_los_Datos#8":"2024-01-13","Fecha_de_Fin_de_los_Datos#9":"2024-02-11","ID_de_la_Campaña#10":"120204157581240570","Impresiones":"20930","Nombre_de_la_Campaña#11":"FBIG_Técnico_Admin_Enero_2024_Cali","Objetivo_de_la_Campaña#12":"OUTCOME_LEADS","Gasto":"65439","Inicio_de_la_Campaña#13":"2024-02-08T18:05:41-0500","Estado_de_la_Campaña#14":"ACTIVE","Clics_Unicos#15":"197"},{"ID_de_la_Cuenta#0":"593096482231018","Nombre_de_la_Cuenta#1":"Nueva America Virtual","Ad_Network#2":"facebook","Estrategia_de_Oferta_de_la_Campaña#3":"None","Clics":"131","CPC__Costo_por_clic_#4":"589.007634","CPM__Costo_por_mil_impresiones_#5":"7155.708059","CTR__Tasa_de_clics_#6":"1.214875","Presupuesto_Diario_de_la_Campaña#7":"None","Fecha_de_Inicio_de_los_Datos#8":"2024-01-13","Fecha_de_Fin_de_los_Datos#9":"2024-02-11","ID_de_la_Campaña#10":"120204021382460570","Impresiones":"10783","Nombre_de_la_Campaña#11":"FBIG_Formulario_BH_Similares","Objetivo_de_la_Campaña#12":"OUTCOME_LEADS","Gasto":"77160","Inicio_de_la_Campaña#13":"2024-02-05T18:25:04-0500","Estado_de_la_Campaña#14":"ACTIVE","Clics_Unicos#15":"102"},{"ID_de_la_Cuenta#0":"593096482231018","Nombre_de_la_Cuenta#1":"Nueva America Virtual","Ad_Network#2":"facebook","Estrategia_de_Oferta_de_la_Campaña#3":"None","Clics":"639","CPC__Costo_por_clic_#4":"301.42723","CPM__Costo_por_mil_impresiones_#5":"5701.953819","CTR__Tasa_de_clics_#6":"1.891652","Presupuesto_Diario_de_la_Campaña#7":"None","Fecha_de_Inicio_de_los_Datos#8":"2024-01-13","Fecha_de_Fin_de_los_Datos#9":"2024-02-11","ID_de_la_Campaña#10":"120204020666220570","Impresiones":"33780","Nombre_de_la_Campaña#11":"FBIG_BH_LEADS_FEBRERO","Objetivo_de_la_Campaña#12":"OUTCOME_LEADS","Gasto":"192612","Inicio_de_la_Campaña#13":"2024-02-05T17:59:27-0500","Estado_de_la_Campaña#14":"ACTIVE","Clics_Unicos#15":"553"},{"ID_de_la_Cuenta#0":"593096482231018","Nombre_de_la_Cuenta#1":"Nueva America Virtual","Ad_Network#2":"facebook","Estrategia_de_Oferta_de_la_Campaña#3":"LOWEST_COST_WITHOUT_CAP","Clics":"426","CPC__Costo_por_clic_#4":"599.255869","CPM__Costo_por_mil_impresiones_#5":"5498.47075","CTR__Tasa_de_clics_#6":"0.91755","Presupuesto_Diario_de_la_Campaña#7":"40000","Fecha_de_Inicio_de_los_Datos#8":"2024-01-13","Fecha_de_Fin_de_los_Datos#9":"2024-02-11","ID_de_la_Campaña#10":"120203889360060570","Impresiones":"46428","Nombre_de_la_Campaña#11":"FBIG_Técnico_Admin_Enero_2024_Medellin","Objetivo_de_la_Campaña#12":"OUTCOME_LEADS","Gasto":"255283","Inicio_de_la_Campaña#13":"2024-02-02T18:06:50-0500","Estado_de_la_Campaña#14":"ACTIVE","Clics_Unicos#15":"337"},{"ID_de_la_Cuenta#0":"593096482231018","Nombre_de_la_Cuenta#1":"Nueva America Virtual","Ad_Network#2":"facebook","Estrategia_de_Oferta_de_la_Campaña#3":"None","Clics":"311","CPC__Costo_por_clic_#4":"250.890675","CPM__Costo_por_mil_impresiones_#5":"6811.016061","CTR__Tasa_de_clics_#6":"2.714735","Presupuesto_Diario_de_la_Campaña#7":"None","Fecha_de_Inicio_de_los_Datos#8":"2024-01-13","Fecha_de_Fin_de_los_Datos#9":"2024-02-11","ID_de_la_Campaña#10":"120203481449190570","Impresiones":"11456","Nombre_de_la_Campaña#11":"FBIG_Técnico_visita_sede","Objetivo_de_la_Campaña#12":"OUTCOME_LEADS","Gasto":"78027","Inicio_de_la_Campaña#13":"2024-01-26T18:29:35-0500","Estado_de_la_Campaña#14":"PAUSED","Clics_Unicos#15":"244"},{"ID_de_la_Cuenta#0":"593096482231018","Nombre_de_la_Cuenta#1":"Nueva America Virtual","Ad_Network#2":"facebook","Estrategia_de_Oferta_de_la_Campaña#3":"None","Clics":"229","CPC__Costo_por_clic_#4":"441.759825","CPM__Costo_por_mil_impresiones_#5":"4765.994535","CTR__Tasa_de_clics_#6":"1.078866","Presupuesto_Diario_de_la_Campaña#7":"None","Fecha_de_Inicio_de_los_Datos#8":"2024-01-13","Fecha_de_Fin_de_los_Datos#9":"2024-02-11","ID_de_la_Campaña#10":"120203477638780570","Impresiones":"21226","Nombre_de_la_Campaña#11":"FBIG_Formulario_BH_VISITA A SEDE","Objetivo_de_la_Campaña#12":"OUTCOME_LEADS","Gasto":"101163","Inicio_de_la_Campaña#13":"2024-01-26T16:58:52-0500","Estado_de_la_Campaña#14":"PAUSED","Clics_Unicos#15":"176"},{"ID_de_la_Cuenta#0":"593096482231018","Nombre_de_la_Cuenta#1":"Nueva America Virtual","Ad_Network#2":"facebook","Estrategia_de_Oferta_de_la_Campaña#3":"LOWEST_COST_WITHOUT_CAP","Clics":"486","CPC__Costo_por_clic_#4":"275.888889","CPM__Costo_por_mil_impresiones_#5":"356.576407","CTR__Tasa_de_clics_#6":"0.129246","Presupuesto_Diario_de_la_Campaña#7":"16000","Fecha_de_Inicio_de_los_Datos#8":"2024-01-13","Fecha_de_Fin_de_los_Datos#9":"2024-02-11","ID_de_la_Campaña#10":"120203372724930570","Impresiones":"376026","Nombre_de_la_Campaña#11":"ORGANICO - ADMIN","Objetivo_de_la_Campaña#12":"OUTCOME_AWARENESS","Gasto":"134082","Inicio_de_la_Campaña#13":"2024-01-23T17:12:47-0500","Estado_de_la_Campaña#14":"PAUSED","Clics_Unicos#15":"481"},{"ID_de_la_Cuenta#0":"593096482231018","Nombre_de_la_Cuenta#1":"Nueva America Virtual","Ad_Network#2":"facebook","Estrategia_de_Oferta_de_la_Campaña#3":"None","Clics":"38755","CPC__Costo_por_clic_#4":"203.760108","CPM__Costo_por_mil_impresiones_#5":"2766.881125","CTR__Tasa_de_clics_#6":"1.357911","Presupuesto_Diario_de_la_Campaña#7":"None","Fecha_de_Inicio_de_los_Datos#8":"2024-01-13","Fecha_de_Fin_de_los_Datos#9":"2024-02-11","ID_de_la_Campaña#10":"120203130531220570","Impresiones":"2854016","Nombre_de_la_Campaña#11":"FBIG_Técnico_Admin_Postobon","Objetivo_de_la_Campaña#12":"OUTCOME_LEADS","Gasto":"7896723","Inicio_de_la_Campaña#13":"2024-01-15T12:00:33-0500","Estado_de_la_Campaña#14":"ACTIVE","Clics_Unicos#15":"27765"},{"ID_de_la_Cuenta#0":"593096482231018","Nombre_de_la_Cuenta#1":"Nueva America Virtual","Ad_Network#2":"facebook","Estrategia_de_Oferta_de_la_Campaña#3":"None","Clics":"19337","CPC__Costo_por_clic_#4":"234.146093","CPM__Costo_por_mil_impresiones_#5":"3476.794153","CTR__Tasa_de_clics_#6":"1.484882","Presupuesto_Diario_de_la_Campaña#7":"None","Fecha_de_Inicio_de_los_Datos#8":"2024-01-13","Fecha_de_Fin_de_los_Datos#9":"2024-02-11","ID_de_la_Campaña#10":"120203129335910570","Impresiones":"1302258","Nombre_de_la_Campaña#11":"FBIG_Técnico_Mercadeo_Postobon","Objetivo_de_la_Campaña#12":"OUTCOME_LEADS","Gasto":"4527683","Inicio_de_la_Campaña#13":"2024-01-15T11:55:00-0500","Estado_de_la_Campaña#14":"ACTIVE","Clics_Unicos#15":"13812"},{"ID_de_la_Cuenta#0":"593096482231018","Nombre_de_la_Cuenta#1":"Nueva America Virtual","Ad_Network#2":"facebook","Estrategia_de_Oferta_de_la_Campaña#3":"LOWEST_COST_WITHOUT_CAP","Clics":"910","CPC__Costo_por_clic_#4":"506.102198","CPM__Costo_por_mil_impresiones_#5":"9125.824796","CTR__Tasa_de_clics_#6":"1.803159","Presupuesto_Diario_de_la_Campaña#7":"13800","Fecha_de_Inicio_de_los_Datos#8":"2024-01-13","Fecha_de_Fin_de_los_Datos#9":"2024-02-11","ID_de_la_Campaña#10":"120202948296740570","Impresiones":"50467","Nombre_de_la_Campaña#11":"FBIG_Formulario_BH_Temp_24","Objetivo_de_la_Campaña#12":"OUTCOME_LEADS","Gasto":"460553","Inicio_de_la_Campaña#13":"2024-01-10T12:59:22-0500","Estado_de_la_Campaña#14":"ACTIVE","Clics_Unicos#15":"649"},{"ID_de_la_Cuenta#0":"593096482231018","Nombre_de_la_Cuenta#1":"Nueva America Virtual","Ad_Network#2":"facebook","Estrategia_de_Oferta_de_la_Campaña#3":"LOWEST_COST_WITHOUT_CAP","Clics":"910","CPC__Costo_por_clic_#4":"506.102198","CPM__Costo_por_mil_impresiones_#5":"9125.824796","CTR__Tasa_de_clics_#6":"1.803159","Presupuesto_Diario_de_la_Campaña#7":"30000","Fecha_de_Inicio_de_los_Datos#8":"2024-01-13","Fecha_de_Fin_de_los_Datos#9":"2024-02-11","ID_de_la_Campaña#10":"120202947979820570","Impresiones":"50467","Nombre_de_la_Campaña#11":"FBIG_Técnico_Procesamiento_Enero_2024","Objetivo_de_la_Campaña#12":"OUTCOME_LEADS","Gasto":"460553","Inicio_de_la_Campaña#13":"2024-01-10T12:39:15-0500","Estado_de_la_Campaña#14":"PAUSED","Clics_Unicos#15":"649"},{"ID_de_la_Cuenta#0":"593096482231018","Nombre_de_la_Cuenta#1":"Nueva America Virtual","Ad_Network#2":"facebook","Estrategia_de_Oferta_de_la_Campaña#3":"LOWEST_COST_WITHOUT_CAP","Clics":"1655","CPC__Costo_por_clic_#4":"543.500302","CPM__Costo_por_mil_impresiones_#5":"7106.740197","CTR__Tasa_de_clics_#6":"1.307587","Presupuesto_Diario_de_la_Campaña#7":"30000","Fecha_de_Inicio_de_los_Datos#8":"2024-01-13","Fecha_de_Fin_de_los_Datos#9":"2024-02-11","ID_de_la_Campaña#10":"120202947797520570","Impresiones":"126569","Nombre_de_la_Campaña#11":"FBIG_Técnico_Hoteleria_Enero_2024","Objetivo_de_la_Campaña#12":"OUTCOME_LEADS","Gasto":"899493","Inicio_de_la_Campaña#13":"2024-01-10T12:24:03-0500","Estado_de_la_Campaña#14":"ACTIVE","Clics_Unicos#15":"1067"},{"ID_de_la_Cuenta#0":"593096482231018","Nombre_de_la_Cuenta#1":"Nueva America Virtual","Ad_Network#2":"facebook","Estrategia_de_Oferta_de_la_Campaña#3":"None","Clics":"1669","CPC__Costo_por_clic_#4":"504.010785","CPM__Costo_por_mil_impresiones_#5":"7009.95","CTR__Tasa_de_clics_#6":"1.390833","Presupuesto_Diario_de_la_Campaña#7":"None","Fecha_de_Inicio_de_los_Datos#8":"2024-01-13","Fecha_de_Fin_de_los_Datos#9":"2024-02-11","ID_de_la_Campaña#10":"120202946980650570","Impresiones":"120000","Nombre_de_la_Campaña#11":"FBIG_Técnico_Admin_Enero_2024","Objetivo_de_la_Campaña#12":"OUTCOME_LEADS","Gasto":"841194","Inicio_de_la_Campaña#13":"2024-01-10T11:58:45-0500","Estado_de_la_Campaña#14":"ACTIVE","Clics_Unicos#15":"1129"},{"ID_de_la_Cuenta#0":"593096482231018","Nombre_de_la_Cuenta#1":"Nueva America Virtual","Ad_Network#2":"facebook","Estrategia_de_Oferta_de_la_Campaña#3":"None","Clics":"410","CPC__Costo_por_clic_#4":"602.243902","CPM__Costo_por_mil_impresiones_#5":"10376.097827","CTR__Tasa_de_clics_#6":"1.722906","Presupuesto_Diario_de_la_Campaña#7":"None","Fecha_de_Inicio_de_los_Datos#8":"2024-01-13","Fecha_de_Fin_de_los_Datos#9":"2024-02-11","ID_de_la_Campaña#10":"120202787625800570","Impresiones":"23797","Nombre_de_la_Campaña#11":"FBIG_Técnico_Mercadeo_Enero_2024","Objetivo_de_la_Campaña#12":"OUTCOME_LEADS","Gasto":"246920","Inicio_de_la_Campaña#13":"2024-01-05T18:00:47-0500","Estado_de_la_Campaña#14":"ACTIVE","Clics_Unicos#15":"272"},{"ID_de_la_Cuenta#0":"593096482231018","Nombre_de_la_Cuenta#1":"Nueva America Virtual","Ad_Network#2":"facebook","Estrategia_de_Oferta_de_la_Campaña#3":"LOWEST_COST_WITHOUT_CAP","Clics":"1607","CPC__Costo_por_clic_#4":"127.807094","CPM__Costo_por_mil_impresiones_#5":"3410.877688","CTR__Tasa_de_clics_#6":"2.66877","Presupuesto_Diario_de_la_Campaña#7":"9000","Fecha_de_Inicio_de_los_Datos#8":"2024-01-13","Fecha_de_Fin_de_los_Datos#9":"2024-02-11","ID_de_la_Campaña#10":"120202758163200570","Impresiones":"60215","Nombre_de_la_Campaña#11":"FBIG_Formulario_BH_Temp_23-24 - lookilike","Objetivo_de_la_Campaña#12":"OUTCOME_LEADS","Gasto":"205386","Inicio_de_la_Campaña#13":"2024-01-04T13:08:10-0500","Estado_de_la_Campaña#14":"ACTIVE","Clics_Unicos#15":"1489"},{"ID_de_la_Cuenta#0":"593096482231018","Nombre_de_la_Cuenta#1":"Nueva America Virtual","Ad_Network#2":"facebook","Estrategia_de_Oferta_de_la_Campaña#3":"LOWEST_COST_WITHOUT_CAP","Clics":"1607","CPC__Costo_por_clic_#4":"127.807094","CPM__Costo_por_mil_impresiones_#5":"3410.877688","CTR__Tasa_de_clics_#6":"2.66877","Presupuesto_Diario_de_la_Campaña#7":"100000","Fecha_de_Inicio_de_los_Datos#8":"2024-01-13","Fecha_de_Fin_de_los_Datos#9":"2024-02-11","ID_de_la_Campaña#10":"120202755091270570","Impresiones":"60215","Nombre_de_la_Campaña#11":"FBIG_Técnico_admin_Falabella - Copia","Objetivo_de_la_Campaña#12":"OUTCOME_LEADS","Gasto":"205386","Inicio_de_la_Campaña#13":"2024-01-04T10:55:26-0500","Estado_de_la_Campaña#14":"PAUSED","Clics_Unicos#15":"1489"},{"ID_de_la_Cuenta#0":"593096482231018","Nombre_de_la_Cuenta#1":"Nueva America Virtual","Ad_Network#2":"facebook","Estrategia_de_Oferta_de_la_Campaña#3":"LOWEST_COST_WITHOUT_CAP","Clics":"6950","CPC__Costo_por_clic_#4":"81.032086","CPM__Costo_por_mil_impresiones_#5":"2357.86208","CTR__Tasa_de_clics_#6":"2.909788","Presupuesto_Diario_de_la_Campaña#7":"5000","Fecha_de_Inicio_de_los_Datos#8":"2024-01-13","Fecha_de_Fin_de_los_Datos#9":"2024-02-11","ID_de_la_Campaña#10":"120202735572880570","Impresiones":"238849","Nombre_de_la_Campaña#11":"FBIG_Formulario_BH_Temp_23-24 - Copia 4","Objetivo_de_la_Campaña#12":"OUTCOME_LEADS","Gasto":"563173","Inicio_de_la_Campaña#13":"2024-01-03T18:03:14-0500","Estado_de_la_Campaña#14":"PAUSED","Clics_Unicos#15":"6374"},{"ID_de_la_Cuenta#0":"593096482231018","Nombre_de_la_Cuenta#1":"Nueva America Virtual","Ad_Network#2":"facebook","Estrategia_de_Oferta_de_la_Campaña#3":"LOWEST_COST_WITHOUT_CAP","Clics":"6950","CPC__Costo_por_clic_#4":"81.032086","CPM__Costo_por_mil_impresiones_#5":"2357.86208","CTR__Tasa_de_clics_#6":"2.909788","Presupuesto_Diario_de_la_Campaña#7":"17000","Fecha_de_Inicio_de_los_Datos#8":"2024-01-13","Fecha_de_Fin_de_los_Datos#9":"2024-02-11","ID_de_la_Campaña#10":"120202735572480570","Impresiones":"238849","Nombre_de_la_Campaña#11":"FBIG_Formulario_BH_Temp_23-24 - Copia 4","Objetivo_de_la_Campaña#12":"OUTCOME_LEADS","Gasto":"563173","Inicio_de_la_Campaña#13":"2024-01-03T18:03:14-0500","Estado_de_la_Campaña#14":"ACTIVE","Clics_Unicos#15":"6374"},{"ID_de_la_Cuenta#0":"593096482231018","Nombre_de_la_Cuenta#1":"Nueva America Virtual","Ad_Network#2":"facebook","Estrategia_de_Oferta_de_la_Campaña#3":"LOWEST_COST_WITHOUT_CAP","Clics":"676","CPC__Costo_por_clic_#4":"326.005917","CPM__Costo_por_mil_impresiones_#5":"3374.058424","CTR__Tasa_de_clics_#6":"1.034968","Presupuesto_Diario_de_la_Campaña#7":"12000","Fecha_de_Inicio_de_los_Datos#8":"2024-01-13","Fecha_de_Fin_de_los_Datos#9":"2024-02-11","ID_de_la_Campaña#10":"120202730866350570","Impresiones":"65316","Nombre_de_la_Campaña#11":"FBIG_Formulario_BH_Temp_23-24 - Copia 3","Objetivo_de_la_Campaña#12":"OUTCOME_LEADS","Gasto":"220380","Inicio_de_la_Campaña#13":"2024-01-03T12:56:05-0500","Estado_de_la_Campaña#14":"ACTIVE","Clics_Unicos#15":"582"},{"ID_de_la_Cuenta#0":"593096482231018","Nombre_de_la_Cuenta#1":"Nueva America Virtual","Ad_Network#2":"facebook","Estrategia_de_Oferta_de_la_Campaña#3":"None","Clics":"1340","CPC__Costo_por_clic_#4":"223.335075","CPM__Costo_por_mil_impresiones_#5":"1960.850991","CTR__Tasa_de_clics_#6":"0.877986","Presupuesto_Diario_de_la_Campaña#7":"None","Fecha_de_Inicio_de_los_Datos#8":"2024-01-13","Fecha_de_Fin_de_los_Datos#9":"2024-02-11","ID_de_la_Campaña#10":"120202624017160570","Impresiones":"152622","Nombre_de_la_Campaña#11":"FBIG_Formulario_BH_Reels_Enero2024","Objetivo_de_la_Campaña#12":"OUTCOME_LEADS","Gasto":"299269","Inicio_de_la_Campaña#13":"2023-12-28T18:15:18-0500","Estado_de_la_Campaña#14":"ACTIVE","Clics_Unicos#15":"1172"},{"ID_de_la_Cuenta#0":"593096482231018","Nombre_de_la_Cuenta#1":"Nueva America Virtual","Ad_Network#2":"facebook","Estrategia_de_Oferta_de_la_Campaña#3":"LOWEST_COST_WITHOUT_CAP","Clics":"1545","CPC__Costo_por_clic_#4":"236.023948","CPM__Costo_por_mil_impresiones_#5":"3792.111229","CTR__Tasa_de_clics_#6":"1.606664","Presupuesto_Diario_de_la_Campaña#7":"16000","Fecha_de_Inicio_de_los_Datos#8":"2024-01-13","Fecha_de_Fin_de_los_Datos#9":"2024-02-11","ID_de_la_Campaña#10":"120202622745350570","Impresiones":"96162","Nombre_de_la_Campaña#11":"FBIG_Formulario_BH_Temp_23-24 - Copia 2","Objetivo_de_la_Campaña#12":"OUTCOME_LEADS","Gasto":"364657","Inicio_de_la_Campaña#13":"2023-12-29T00:02:42-0500","Estado_de_la_Campaña#14":"ACTIVE","Clics_Unicos#15":"1324"},{"ID_de_la_Cuenta#0":"593096482231018","Nombre_de_la_Cuenta#1":"Nueva America Virtual","Ad_Network#2":"facebook","Estrategia_de_Oferta_de_la_Campaña#3":"LOWEST_COST_WITHOUT_CAP","Clics":"10646","CPC__Costo_por_clic_#4":"144.855345","CPM__Costo_por_mil_impresiones_#5":"2743.783861","CTR__Tasa_de_clics_#6":"1.894154","Presupuesto_Diario_de_la_Campaña#7":"26000","Fecha_de_Inicio_de_los_Datos#8":"2024-01-13","Fecha_de_Fin_de_los_Datos#9":"2024-02-11","ID_de_la_Campaña#10":"120202451807310570","Impresiones":"562045","Nombre_de_la_Campaña#11":"FBIG_Formulario_BH_Temp_23-24 - Copia","Objetivo_de_la_Campaña#12":"OUTCOME_LEADS","Gasto":"1542130","Inicio_de_la_Campaña#13":"2023-12-21T15:30:41-0500","Estado_de_la_Campaña#14":"ACTIVE","Clics_Unicos#15":"9379"}]